Workbook

Sheet README
A1: Flipbook — Financial Model
A3: Version: v1 (July 15, 2026)
A4: Companion doc: docs/model-math.md
A6: HOW TO USE
A7: All INPUT cells are BLUE text with YELLOW highlight. Change those. Everything else is a formula.
A9: Tabs:
A10: Assumptions — inputs. Start here.
A11: Unit Econ — per-rental and per-user math.
A12: Projection — 12-month monthly P&L.
A13: Sensitivity — what-if analysis on 6 biggest levers.
A14: Scenarios — Conservative / Base / Stretch side-by-side.
A16: CURRENCY
... A30: book-rental app because there is not one yet.

Sheet Assumptions
A1: Assumptions
A2: Yellow cells are the ones to tune. Everything downstream is formulas.
A4: CURRENCY
A5: NGN per USD | B5: 1500 | D5: FX rate.
A7: RENTAL BANDS (LOCKED)
A8: Band A price | B8: 500 | D8: PD classics — 4-week rental
A9: Band B price | B9: 1500 | D9: Indie standard
A10: Band C price | B10: 2500 | D10: Premium indie / small publisher
A11: Band D price | B11: 4000 | D11: Later — Tier 3 publisher titles
A13: PRO PRICING
A14: Pro monthly | B14: 2500 | D14: Full monthly rate
A15: Pro quarterly (mo effective) | B15: 2000 | D15: 6,000 per quarter
A16: Pro annual (mo effective) | B16: 1550 | D16: 18,600 per year — 38% discount vs monthly
A17: Mix — monthly | B17: 0.3
A18: Mix — quarterly | B18: 0.4
A19: Mix — annual | B19: 0.3
A20: Blended Pro ARPU (mo) | B20: =B14*B17+B15*B18+B16*B19 -> 2015
A22: REVENUE SHARE
A23: Author share | B23: 0.7
A24: Flipbook share | B24: =1-B23 -> 0.3
A25: Pro discount on B/C/D | B25: 0.15
A27: READER BEHAVIOR (SPECULATIVE)
A28: Rentals per Free user per month | B28: 0.7
A29: Rentals per Pro user per month | B29: 4
A30: Free band mix A | B30: 0.3
A31: Free band mix B | B31: 0.6
A32: Free band mix C | B32: 0.1
A33: Blended Free rental price | B33: =B8*B30+B9*B31+B10*B32 -> 1300
A34: Pro band mix B | B34: 0.8
A35: Pro band mix C | B35: 0.2
A36: Blended Pro rental price after 15% discount | B36: =(B9*B34+B10*B35)*(1-B25) -> 1445
A38: COSTS
A39: Payment processing (blended %) | B39: 0.02
A40: TTS ingestion cost per title | B40: 9000
A41: New titles ingested per month | B41: 50
A42: Specials indie flat fees (mo) | B42: 75000
A43: Specials premium narration (mo amortized) | B43: 62500
A44: Payment failure rate | B44: 0.12

Sheet Unit Econ
A1: Unit Economics — Per Rental
A2: Flipbook contribution per rental, by band and reader type.
B4: A Free | C4: A Pro | D4: B Free | E4: B Pro | F4: C Free | G4: C Pro | H4: D Free | I4: D Pro
A5: List price | B5: =Assumptions!B8 -> 500 | C5: =Assumptions!B8 -> 500 | D5: =Assumptions!B9 -> 1500 | E5: =Assumptions!B9 -> 1500 | F5: =Assumptions!B10 -> 2500 | G5: =Assumptions!B10 -> 2500 | H5: =Assumptions!B11 -> 4000 | I5: =Assumptions!B11 -> 4000
A6: Price paid | B6: =B5 -> 500 | C6: =0 -> 0 | D6: =D5 -> 1500 | E6: =D5*(1-Assumptions!B25) -> 1275 | F6: =F5 -> 2500 | G6: =F5*(1-Assumptions!B25) -> 2125 | H6: =H5 -> 4000 | I6: =H5*(1-Assumptions!B25) -> 3400
A7: Author cut (70%) | B7: =B6*Assumptions!B23 -> 350 | C7: =C6*Assumptions!B23 -> 0 | D7: =D6*Assumptions!B23 -> 1050 | E7: =E6*Assumptions!B23 -> 892.5 | F7: =F6*Assumptions!B23 -> 1750 | G7: =G6*Assumptions!B23 -> 1487.5 | H7: =H6*Assumptions!B23 -> 2800 | I7: =I6*Assumptions!B23 -> 2380
A8: Flipbook cut (30%) | B8: =B6*Assumptions!B24 -> 150 | C8: =C6*Assumptions!B24 -> 0 | D8: =D6*Assumptions!B24 -> 450 | E8: =E6*Assumptions!B24 -> 382.5 | F8: =F6*Assumptions!B24 -> 750 | G8: =G6*Assumptions!B24 -> 637.5 | H8: =H6*Assumptions!B24 -> 1200 | I8: =I6*Assumptions!B24 -> 1020
A9: Payment fee | B9: =B6*Assumptions!B39 -> 10 | C9: =C6*Assumptions!B39 -> 0 | D9: =D6*Assumptions!B39 -> 30 | E9: =E6*Assumptions!B39 -> 25.5 | F9: =F6*Assumptions!B39 -> 50 | G9: =G6*Assumptions!B39 -> 42.5 | H9: =H6*Assumptions!B39 -> 80 | I9: =I6*Assumptions!B39 -> 68
A10: Flipbook net contribution | B10: =B8-B9 -> 140 | C10: =C8-C9 -> 0 | D10: =D8-D9 -> 420 | E10: =E8-E9 -> 357 | F10: =F8-F9 -> 700 | G10: =G8-G9 -> 595 | H10: =H8-H9 -> 1120 | I10: =I8-I9 -> 952
A12: Unit Economics — Per User Per Month
A13: Pro users are ~14x more valuable than Free users. This is the north star.
B15: Free user | C15: Pro user
A16: Subscription revenue | B16: =0 -> 0 | C16: =Assumptions!B20 -> 2015
A17: Rentals per month | B17: =Assumptions!B28 -> 0.7 | C17: =Assumptions!B29 -> 4
A18: Blended price paid | B18: =Assumptions!B33 -> 1300 | C18: =Assumptions!B36 -> 1445
A19: Gross rental revenue | B19: =B17*B18 -> 910 | C19: =C17*C18 -> 5780
A20: Flipbook 30% of rentals | B20: =B19*Assumptions!B24 -> 273 | C20: =C19*Assumptions!B24 -> 1734
A21: Payment fee on revenue | B21: =(B16+B19)*Assumptions!B39 -> 18.2 | C21: =(C16+C19)*Assumptions!B39 -> 155.9
A22: Net contribution per user per month | B22: =B16+B20-B21 -> 254.8 | C22: =C16+C20-C21 -> 3593.1
A24: Pro-to-Free value ratio | B24: =IFERROR(C22/B22,0) -> 14.101648

Sheet Projection
A1: 12-Month Projection
A2: Active users and Pro conversion % are tunable inputs. Everything else flows.
B4: Oct '26 | C4: Nov '26 | D4: Dec '26 | E4: Jan '27 | F4: Feb '27 | G4: Mar '27 | H4: Apr '27 | I4: May '27 | J4: Jun '27 | K4: Jul '27 | L4: Aug '27 | M4: Sep '27 | N4: Total
A5: USERS
A6: Active users (input) | B6: 200 | C6: 400 | D6: 700 | E6: 1000 | F6: 1500 | G6: 2000 | H6: 2750 | I6: 3500 | J6: 4000 | K6: 4500 | L6: 4800 | M6: 5000
A7: Pro conversion % (input) | B7: 0.05 | C7: 0.055 | D7: 0.057 | E7: 0.06 | F7: 0.063 | G7: 0.0675 | H7: 0.071 | I7: 0.074 | J7: 0.0775 | K7: 0.078 | L7: 0.079 | M7: 0.08
A8: Pro users | B8: =ROUND(B6*B7,0) -> 10 | C8: =ROUND(C6*C7,0) -> 22 | D8: =ROUND(D6*D7,0) -> 40 | E8: =ROUND(E6*E7,0) -> 60 | F8: =ROUND(F6*F7,0) -> 95 | G8: =ROUND(G6*G7,0) -> 135 | H8: =ROUND(H6*H7,0) -> 195 | I8: =ROUND(I6*I7,0) -> 259 | ... M8: =ROUND(M6*M7,0) -> 400
A9: Free users | B9: =B6-B8 -> 190 | C9: =C6-C8 -> 378 | D9: =D6-D8 -> 660 | E9: =E6-E8 -> 940 | F9: =F6-F8 -> 1405 | G9: =G6-G8 -> 1865 | H9: =H6-H8 -> 2555 | I9: =I6-I8 -> 3241 | ... M9: =M6-M8 -> 4600
A11: REVENUE
A12: Pro subscription revenue | B12: =B8*Assumptions!B20 -> 20150 | C12: =C8*Assumptions!B20 -> 44330 | D12: =D8*Assumptions!B20 -> 80600 | E12: =E8*Assumptions!B20 -> 120900 | F12: =F8*Assumptions!B20 -> 191425 | G12: =G8*Assumptions!B20 -> 272025 | H12: =H8*Assumptions!B20 -> 392925 | I12: =I8*Assumptions!B20 -> 521885 | J12: =J8*Assumptions!B20 -> 624650 | K12: =K8*Assumptions!B20 -> 707265 | L12: =L8*Assumptions!B20 -> 763685 | M12: =M8*Assumptions!B20 -> 806000 | N12: =SUM(B12:M12) -> 4545840
A13: Gross rentals (Free) | B13: =B9*Assumptions!B28*Assumptions!B33 -> 172900 | C13: =C9*Assumptions!B28*Assumptions!B33 -> 343980 | D13: =D9*Assumptions!B28*Assumptions!B33 -> 600600 | E13: =E9*Assumptions!B28*Assumptions!B33 -> 855400 | F13: =F9*Assumptions!B28*Assumptions!B33 -> 1278550 | G13: =G9*Assumptions!B28*Assumptions!B33 -> 1697150 | H13: =H9*Assumptions!B28*Assumptions!B33 -> 2325050 | I13: =I9*Assumptions!B28*Assumptions!B33 -> 2949310 | J13: =J9*Assumptions!B28*Assumptions!B33 -> 3357900 | K13: =K9*Assumptions!B28*Assumptions!B33 -> 3775590 | L13: =L9*Assumptions!B28*Assumptions!B33 -> 4023110 | M13: =M9*Assumptions!B28*Assumptions!B33 -> 4186000 | N13: =SUM(B13:M13) -> 25565540
A14: Gross rentals (Pro) | B14: =B8*Assumptions!B29*Assumptions!B36 -> 57800 | C14: =C8*Assumptions!B29*Assumptions!B36 -> 127160 | D14: =D8*Assumptions!B29*Assumptions!B36 -> 231200 | E14: =E8*Assumptions!B29*Assumptions!B36 -> 346800 | F14: =F8*Assumptions!B29*Assumptions!B36 -> 549100 | G14: =G8*Assumptions!B29*Assumptions!B36 -> 780300 | H14: =H8*Assumptions!B29*Assumptions!B36 -> 1127100 | I14: =I8*Assumptions!B29*Assumptions!B36 -> 1497020 | J14: =J8*Assumptions!B29*Assumptions!B36 -> 1791800 | K14: =K8*Assumptions!B29*Assumptions!B36 -> 2028780 | L14: =L8*Assumptions!B29*Assumptions!B36 -> 2190620 | M14: =M8*Assumptions!B29*Assumptions!B36 -> 2312000 | N14: =SUM(B14:M14) -> 13039680
A15: Total gross rentals | B15: =B13+B14 -> 230700 | C15: =C13+C14 -> 471140 | D15: =D13+D14 -> 831800 | E15: =E13+E14 -> 1202200 | F15: =F13+F14 -> 1827650 | G15: =G13+G14 -> 2477450 | H15: =H13+H14 -> 3452150 | I15: =I13+I14 -> 4446330 | ... M15: =M13+M14 -> 6498000 | N15: =SUM(B15:M15) -> 38605220
A16: Flipbook rental cut (30%) | B16: =B15*Assumptions!B24 -> 69210 | C16: =C15*Assumptions!B24 -> 141342 | D16: =D15*Assumptions!B24 -> 249540 | E16: =E15*Assumptions!B24 -> 360660 | F16: =F15*Assumptions!B24 -> 548295 | G16: =G15*Assumptions!B24 -> 743235 | H16: =H15*Assumptions!B24 -> 1035645 | I16: =I15*Assumptions!B24 -> 1333899 | J16: =J15*Assumptions!B24 -> 1544910 | K16: =K15*Assumptions!B24 -> 1741311 | L16: =L15*Assumptions!B24 -> 1864119 | M16: =M15*Assumptions!B24 -> 1949400 | N16: =SUM(B16:M16) -> 11581566
A17: TOTAL FLIPBOOK REVENUE | B17: =B12+B16 -> 89360 | C17: =C12+C16 -> 185672 | D17: =D12+D16 -> 330140 | E17: =E12+E16 -> 481560 | F17: =F12+F16 -> 739720 | G17: =G12+G16 -> 1015260 | H17: =H12+H16 -> 1428570 | I17: =I12+I16 -> 1855784 | ... M17: =M12+M16 -> 2755400 | N17: =SUM(B17:M17) -> 16127406
A19: COSTS
A20: Payment processing (2%) | B20: =(B12+B15)*Assumptions!B39 -> 5017 | C20: =(C12+C15)*Assumptions!B39 -> 10309.4 | D20: =(D12+D15)*Assumptions!B39 -> 18248 | E20: =(E12+E15)*Assumptions!B39 -> 26462 | F20: =(F12+F15)*Assumptions!B39 -> 40381.5 | G20: =(G12+G15)*Assumptions!B39 -> 54989.5 | H20: =(H12+H15)*Assumptions!B39 -> 76901.5 | I20: =(I12+I15)*Assumptions!B39 -> 99364.3 | J20: =(J12+J15)*Assumptions!B39 -> 115487 | K20: =(K12+K15)*Assumptions!B39 -> 130232.7 | L20: =(L12+L15)*Assumptions!B39 -> 139548.3 | M20: =(M12+M15)*Assumptions!B39 -> 146080 | N20: =SUM(B20:M20) -> 863021.2
A21: TTS ingestion | B21: =Assumptions!B41*Assumptions!B40 -> 450000 | C21: =Assumptions!B41*Assumptions!B40 -> 450000 | D21: =Assumptions!B41*Assumptions!B40 -> 450000 | E21: =Assumptions!B41*Assumptions!B40 -> 450000 | F21: =Assumptions!B41*Assumptions!B40 -> 450000 | G21: =Assumptions!B41*Assumptions!B40 -> 450000 | H21: =Assumptions!B41*Assumptions!B40 -> 450000 | I21: =Assumptions!B41*Assumptions!B40 -> 450000 | J21: =Assumptions!B41*Assumptions!B40 -> 450000 | K21: =Assumptions!B41*Assumptions!B40 -> 450000 | L21: =Assumptions!B41*Assumptions!B40 -> 450000 | M21: =Assumptions!B41*Assumptions!B40 -> 450000 | N21: =SUM(B21:M21) -> 5400000
A22: Specials indie flat fees | B22: =Assumptions!B42 -> 75000 | C22: =Assumptions!B42 -> 75000 | D22: =Assumptions!B42 -> 75000 | E22: =Assumptions!B42 -> 75000 | F22: =Assumptions!B42 -> 75000 | G22: =Assumptions!B42 -> 75000 | H22: =Assumptions!B42 -> 75000 | I22: =Assumptions!B42 -> 75000 | J22: =Assumptions!B42 -> 75000 | K22: =Assumptions!B42 -> 75000 | L22: =Assumptions!B42 -> 75000 | M22: =Assumptions!B42 -> 75000 | N22: =SUM(B22:M22) -> 900000
A23: Specials premium narration (amortized) | B23: =Assumptions!B43 -> 62500 | C23: =Assumptions!B43 -> 62500 | D23: =Assumptions!B43 -> 62500 | E23: =Assumptions!B43 -> 62500 | F23: =Assumptions!B43 -> 62500 | G23: =Assumptions!B43 -> 62500 | H23: =Assumptions!B43 -> 62500 | I23: =Assumptions!B43 -> 62500 | J23: =Assumptions!B43 -> 62500 | K23: =Assumptions!B43 -> 62500 | L23: =Assumptions!B43 -> 62500 | M23: =Assumptions!B43 -> 62500 | N23: =SUM(B23:M23) -> 750000
A24: Hosting + tools (walks) | B24: 37500 | C24: 37500 | D24: 37500 | E24: 60000 | F24: 60000 | G24: 60000 | H24: 100000 | I24: 100000 | J24: 100000 | K24: 150000 | L24: 150000 | M24: 150000 | N24: =SUM(B24:M24) -> 1042500
A25: TOTAL COSTS | B25: =SUM(B20:B24) -> 630017 | C25: =SUM(C20:C24) -> 635309.4 | D25: =SUM(D20:D24) -> 643248 | E25: =SUM(E20:E24) -> 673962 | F25: =SUM(F20:F24) -> 687881.5 | G25: =SUM(G20:G24) -> 702489.5 | H25: =SUM(H20:H24) -> 764401.5 | I25: =SUM(I20:I24) -> 786864.3 | ... M25: =SUM(M20:M24) -> 883580 | N25: =SUM(B25:M25) -> 8955521.2
A27: CONTRIBUTION
A28: Monthly net contribution | B28: =B17-B25 -> -540657 | C28: =C17-C25 -> -449637.4 | D28: =D17-D25 -> -313108 | E28: =E17-E25 -> -192402 | F28: =F17-F25 -> 51838.5 | G28: =G17-G25 -> 312770.5 | H28: =H17-H25 -> 664168.5 | I28: =I17-I25 -> 1068919.7 | ... M28: =M17-M25 -> 1871820 | N28: =SUM(B28:M28) -> 7171884.8
A29: Cumulative | B29: =B28 -> -540657 | C29: =B29+C28 -> -990294.4 | D29: =C29+D28 -> -1303402.4 | E29: =D29+E28 -> -1495804.4 | F29: =E29+F28 -> -1443965.9 | G29: =F29+G28 -> -1131195.4 | H29: =G29+H28 -> -467026.9 | I29: =H29+I28 -> 601892.8 | J29: =I29+J28 -> 1968465.8 | ... M29: =L29+M28 -> 7171884.8

Sheet Sensitivity
A1: Sensitivity — Levers Ranked by Impact
A2: Month-12 monthly contribution swing between Low and High for each lever.
A4: Lever | B4: Base | C4: Low | D4: High | E4: Delta (Low->High) | F4: Notes
A5: Pro conversion at Month 12 | B5: 8% | C5: 3% | D5: 12% | E5: =(0.12-0.03)*Projection!M6*Assumptions!B20 -> 906750 | F5: Biggest lever. Audio reader + Specials most influence.
A6: Rentals per Free user per month | B6: 0.7 | C6: 0.3 | D6: 1.2 | E6: =(1.2-0.3)*Projection!M9*Assumptions!B33*Assumptions!B24 -> 1614600 | F6: Second biggest. Selection quality + discovery UX.
A7: Rentals per Pro user per month | B7: 4 | C7: 2 | D7: 6 | E7: =(6-2)*Projection!M8*Assumptions!B36*Assumptions!B24 -> 693600 | F7: Pro engagement — habit + catalog depth.
A8: Active users at Month 12 | B8: 5,000 | C8: 2,500 | D8: 8,000 | E8: =((8000-2500)/Projection!M6)*(Projection!M12+Projection!M16) -> 3030940 | F8: Growth. Everything scales on this.
A9: TTS titles per month | B9: 50 | C9: 25 | D9: 100 | E9: =-(100-25)*Assumptions!B40 -> -675000 | F9: Cost lever (inverse). More content = more cost.
A10: Payment failure rate | B10: 12% | C10: 5% | D10: 20% | E10: =-(0.2-0.05)*(Projection!M12+Projection!M16) -> -413310 | F10: Good rebill logic recovers half.
A13: Breakeven Analysis
A14: Monthly breakeven happens when total revenue = total costs.
A16: Total monthly cost (fixed + variable at breakeven scale) | B16: =Assumptions!B41*Assumptions!B40+Assumptions!B42+Assumptions!B43+100000 -> 687500
A17: Revenue per Free user per month | B17: =Assumptions!B28*Assumptions!B33*Assumptions!B24*(1-Assumptions!B39) -> 267.54
A18: Revenue per Pro user per month | B18: =Assumptions!B20+Assumptions!B29*Assumptions!B36*Assumptions!B24-(Assumptions!B20+Assumptions!B29*Assumptions!B36)*Assumptions!B39 -> 3593.1
A19: Assumed Pro conversion for breakeven | B19: 0.07
A20: Blended revenue per active user per month | B20: =B17*(1-B19)+B18*B19 -> 500.3292
A21: Active users needed for monthly breakeven | B21: =IFERROR(ROUND(B16/B20,0),0) -> 1374
A22: Pro users needed for monthly breakeven | B22: =ROUND(B21*B19,0) -> 96

Sheet Scenarios
A1: Scenarios — Conservative / Base / Stretch
A2: Three futures at Month 12. Base matches the Projection tab.
A4: Metric | B4: Conservative | C4: Base | D4: Stretch
A5: Active users at Month 12 | B5: 2500 | C5: 5000 | D5: 8000
A6: Pro conversion at Month 12 | B6: 0.05 | C6: 0.08 | D6: 0.12
A7: Rentals per Free user per month | B7: 0.4 | C7: 0.7 | D7: 1
A8: Rentals per Pro user per month | B8: 3 | C8: 4 | D8: 5
A10: Pro users | B10: =ROUND(B5*B6,0) -> 125 | C10: =ROUND(C5*C6,0) -> 400 | D10: =ROUND(D5*D6,0) -> 960
A11: Free users | B11: =B5-B10 -> 2375 | C11: =C5-C10 -> 4600 | D11: =D5-D10 -> 7040
A12: Monthly Pro subscription revenue | B12: =B10*Assumptions!B20 -> 251875 | C12: =C10*Assumptions!B20 -> 806000 | D12: =D10*Assumptions!B20 -> 1934400
A13: Monthly gross rentals | B13: =B11*B7*Assumptions!B33+B10*B8*Assumptions!B36 -> 1776875 | C13: =C11*C7*Assumptions!B33+C10*C8*Assumptions!B36 -> 6498000 | D13: =D11*D7*Assumptions!B33+D10*D8*Assumptions!B36 -> 16088000
A14: Monthly Flipbook rental cut | B14: =B13*Assumptions!B24 -> 533062.5 | C14: =C13*Assumptions!B24 -> 1949400 | D14: =D13*Assumptions!B24 -> 4826400
A15: Monthly TOTAL revenue | B15: =B12+B14 -> 784937.5 | C15: =C12+C14 -> 2755400 | D15: =D12+D14 -> 6760800
A16: Monthly total costs | B16: =(B12+B13)*Assumptions!B39+Assumptions!B41*Assumptions!B40+Assumptions!B42+Assumptions!B43+150000 -> 778075 | C16: =(C12+C13)*Assumptions!B39+Assumptions!B41*Assumptions!B40+Assumptions!B42+Assumptions!B43+150000 -> 883580 | D16: =(D12+D13)*Assumptions!B39+Assumptions!B41*Assumptions!B40+Assumptions!B42+Assumptions!B43+150000 -> 1097948
A17: Monthly NET CONTRIBUTION | B17: =B15-B16 -> 6862.5 | C17: =C15-C16 -> 1871820 | D17: =D15-D16 -> 5662852
A18: Contribution in USD | B18: =B17/Assumptions!B5 -> 4.575 | C18: =C17/Assumptions!B5 -> 1247.88 | D18: =D17/Assumptions!B5 -> 3775.2347
A20: Reading the Scenarios
A21: Conservative: half the users, lowest Pro conversion, sluggish rentals.
A22: Base: current growth curve on Projection tab.
A23: Stretch: audio + Specials + community compound.
A25: If Conservative contribution is positive, we can miss numbers by 50% and survive.
A26: If Conservative is negative, the model is fragile — tune growth or costs.
